kitconcept.dsgvo-2.0.1-py3.10-nspkg.pth
kitconcept/dsgvo/__init__.py
kitconcept/dsgvo/configure.zcml
kitconcept/dsgvo/contactform.py
kitconcept/dsgvo/dependencies.zcml
kitconcept/dsgvo/events.py
kitconcept/dsgvo/interfaces.py
kitconcept/dsgvo/mailchimp.py
kitconcept/dsgvo/setuphandlers.py
kitconcept/dsgvo/testing.py
kitconcept/dsgvo/userdataschema.py
kitconcept/dsgvo/userdataschema_p4.py
kitconcept/dsgvo/util.py
kitconcept/dsgvo/viewlet.pt
kitconcept/dsgvo/viewlet.py
kitconcept/dsgvo/widget.py
kitconcept/dsgvo/browser/__init__.py
kitconcept/dsgvo/browser/configure.zcml
kitconcept/dsgvo/browser/info.py
kitconcept/dsgvo/browser/users.py
kitconcept/dsgvo/browser/overrides/.gitkeep
kitconcept/dsgvo/browser/overrides/Products.CMFPlone.skins.plone_templates.contact-info.cpt
kitconcept/dsgvo/browser/static/.gitkeep
kitconcept/dsgvo/browser/static/dsgvo.css
kitconcept/dsgvo/browser/static/dsgvo.js
kitconcept/dsgvo/locales/kitconcept.dsgvo.pot
kitconcept/dsgvo/locales/update.sh
kitconcept/dsgvo/locales/de/LC_MESSAGES/kitconcept.dsgvo.po
kitconcept/dsgvo/locales/en/LC_MESSAGES/kitconcept.dsgvo.po
kitconcept/dsgvo/locales/fr/LC_MESSAGES/kitconcept.dsgvo.po
kitconcept/dsgvo/locales/no/LC_MESSAGES/kitconcept.dsgvo.po
kitconcept/dsgvo/profiles/common/memberdata_properties.xml
kitconcept/dsgvo/profiles/common/metadata.xml
kitconcept/dsgvo/profiles/plone5/browserlayer.xml
kitconcept/dsgvo/profiles/plone5/cssregistry.xml
kitconcept/dsgvo/profiles/plone5/jsregistry.xml
kitconcept/dsgvo/profiles/plone5/metadata.xml
kitconcept/dsgvo/profiles/plone5/registry.xml
kitconcept/dsgvo/profiles/uninstall/browserlayer.xml
kitconcept/dsgvo/templates/checkbox_display.pt
kitconcept/dsgvo/templates/checkbox_hidden.pt
kitconcept/dsgvo/templates/checkbox_input.pt
kitconcept/dsgvo/tests/__init__.py
kitconcept/dsgvo/tests/test_robot.py
kitconcept/dsgvo/tests/test_setup.py
kitconcept/dsgvo/tests/test_views.py
kitconcept/dsgvo/tests/robot/test_example.robot
kitconcept.dsgvo-2.0.1.dist-info/LICENSE.GPL
kitconcept.dsgvo-2.0.1.dist-info/METADATA
kitconcept.dsgvo-2.0.1.dist-info/WHEEL
kitconcept.dsgvo-2.0.1.dist-info/entry_points.txt
kitconcept.dsgvo-2.0.1.dist-info/namespace_packages.txt
kitconcept.dsgvo-2.0.1.dist-info/top_level.txt
kitconcept.dsgvo-2.0.1.dist-info/RECORD
