Metadata-Version: 2.1
Name: kitconcept.dsgvo
Version: 2.0.1
Summary: DSGVO / GDPR compliance for Plone
Home-page: https://pypi.python.org/pypi/kitconcept.dsgvo
Author: kitconcept GmbH
Author-email: info@kitconcept.com
License: GPL version 2
Keywords: Python Plone DSVGO GDPR
Classifier: Environment :: Web Environment
Classifier: Development Status :: 5 - Production/Stable
Classifier: Framework :: Plone
Classifier: Framework :: Plone :: 5.2
Classifier: Framework :: Plone :: 6.0
Classifier: Programming Language :: Python
Classifier: Programming Language :: Python :: 3.7
Classifier: Programming Language :: Python :: 3.8
Classifier: Programming Language :: Python :: 3.9
Classifier: Operating System :: OS Independent
Classifier: License :: OSI Approved :: GNU General Public License v2 (GPLv2)
Requires-Python: >=3.7
License-File: LICENSE.GPL
Requires-Dist: plone.api
Requires-Dist: Products.CMFPlone
Requires-Dist: setuptools
Requires-Dist: z3c.jbot
Requires-Dist: plone.app.z3cform
Provides-Extra: test
Requires-Dist: plone.app.testing ; extra == 'test'
Requires-Dist: plone.testing ; extra == 'test'
Requires-Dist: plone.app.contenttypes ; extra == 'test'
Requires-Dist: plone.app.robotframework[debug] ; extra == 'test'
Requires-Dist: collective.mailchimp ; extra == 'test'
Requires-Dist: zest.releaser[recommended] ; extra == 'test'
Requires-Dist: zestreleaser.towncrier ; extra == 'test'
